monkai_agent/groq/__init__.py
monkai_agent/groq/__providers.py
monkai_agent/groq/gorq_test.py
monkai_agent_groq-0.1.1.dist-info/METADATA
monkai_agent_groq-0.1.1.dist-info/WHEEL
monkai_agent_groq-0.1.1.dist-info/RECORD
